{
  "metadata": {
    "generated_at": "2026-04-15T03:31:05.200146Z",
    "dataset": "historical",
    "source": "https://csrc.nist.gov/projects/cryptographic-module-validation-program/certificate/1725"
  },
  "certificate": {
    "certificate_number": "1725",
    "dataset": "historical",
    "generated_at": "2026-04-15T03:31:05.200146Z",
    "nist_page_url": "https://csrc.nist.gov/projects/cryptographic-module-validation-program/certificate/1725",
    "certificate_detail_url": "https://csrc.nist.gov/projects/cryptographic-module-validation-program/certificate/1725",
    "security_policy_url": "https://csrc.nist.gov/CSRC/media/projects/cryptographic-module-validation-program/documents/security-policies/140sp1725.pdf",
    "vendor_name": "Francotyp-Postalia GmbH",
    "module_name": "Postal mRevenector DE 2011",
    "standard": "FIPS 140-2",
    "status": "Historical",
    "module_type": "Hardware",
    "embodiment": "Multi-chip embedded",
    "overall_level": 3,
    "validation_date": "5/29/2012, 1/22/2013, 3/13/2015",
    "validation_dates": [
      "5/29/2012",
      "1/22/2013",
      "3/13/2015"
    ],
    "sunset_date": null,
    "caveat": "None",
    "description": "The Francotyp-Postalia Postal mRevenector DE 2011 employs strong encryption, decryption, and digital signature techniques for the protection of customer revenues in Francotyp-Postalia's mail handlers. The Postal mRevenector DE 2011 has been designed in compliance with the Deutsche Post (DPAG), FRANKIT Specification.",
    "security_level_exceptions": [
      "Physical Security: Level 3 +EFP/EFT"
    ],
    "related_files": [
      {
        "label": "Security Policy",
        "url": "https://csrc.nist.gov/CSRC/media/projects/cryptographic-module-validation-program/documents/security-policies/140sp1725.pdf"
      },
      {
        "label": "Consolidated Certificate",
        "url": "https://csrc.nist.gov/CSRC/media/projects/cryptographic-module-validation-program/documents/certificates/FIPS140ConsolidatedCertList0017.pdf"
      }
    ],
    "validation_history": [
      {
        "date": "5/29/2012",
        "type": "Initial",
        "lab": "UL Verification Services, Inc."
      },
      {
        "date": "1/22/2013",
        "type": "Update",
        "lab": "UL Verification Services, Inc."
      },
      {
        "date": "3/13/2015",
        "type": "Update",
        "lab": "UL Verification Services, Inc."
      }
    ],
    "vendor": {
      "name": "Francotyp-Postalia GmbH",
      "website_url": "http://www.francotyp.com",
      "address_lines": [
        "Triftweg 21-26",
        "Birkenwerder D-16547",
        "Germany"
      ],
      "country": "Germany",
      "contact_name": "Dirk Rosenau",
      "contact_email": "d.rosenau@francotyp.com",
      "contact_phone": "+49-3303-525-616"
    }
  }
}