{
  "metadata": {
    "generated_at": "2026-04-14T03:31:23.958455Z",
    "dataset": "historical",
    "source": "https://csrc.nist.gov/projects/cryptographic-module-validation-program/certificate/1811"
  },
  "certificate": {
    "certificate_number": "1811",
    "dataset": "historical",
    "generated_at": "2026-04-14T03:31:23.958455Z",
    "nist_page_url": "https://csrc.nist.gov/projects/cryptographic-module-validation-program/certificate/1811",
    "certificate_detail_url": "https://csrc.nist.gov/projects/cryptographic-module-validation-program/certificate/1811",
    "security_policy_url": "https://csrc.nist.gov/CSRC/media/projects/cryptographic-module-validation-program/documents/security-policies/140sp1811.pdf",
    "vendor_name": "IMS Health Inc.",
    "module_name": "Diversinet Java Crypto Module",
    "standard": "FIPS 140-2",
    "status": "Historical",
    "module_type": "Software",
    "embodiment": "Multi-chip standalone",
    "overall_level": 1,
    "validation_date": "10/11/2012, 2/20/2014",
    "validation_dates": [
      "10/11/2012",
      "2/20/2014"
    ],
    "sunset_date": null,
    "caveat": "None",
    "description": "Diversinet Java SE Crypto Module is a JCA (Java Cryptography Architecture) Provider shipped with Diversinet MobiSecure Products. The Crypto Module implements several JCE (Java Cryptography Extension) algorithms including Triple DES, AES, SHA, HMAC and RSA. The Crypto Module is packaged in a signed Java Archive (JAR) file.",
    "security_level_exceptions": [],
    "related_files": [
      {
        "label": "Security Policy",
        "url": "https://csrc.nist.gov/CSRC/media/projects/cryptographic-module-validation-program/documents/security-policies/140sp1811.pdf"
      },
      {
        "label": "Consolidated Certificate",
        "url": "https://csrc.nist.gov/CSRC/media/projects/cryptographic-module-validation-program/documents/certificates/FIPS140ConsolidatedCertList0022.pdf"
      }
    ],
    "validation_history": [
      {
        "date": "10/11/2012",
        "type": "Initial",
        "lab": "CGI Information Systems & Management Consultants Inc"
      },
      {
        "date": "2/20/2014",
        "type": "Update",
        "lab": "CGI Information Systems & Management Consultants Inc"
      }
    ],
    "vendor": {
      "name": "IMS Health Inc.",
      "website_url": "http://www.diversinet.com",
      "address_lines": [
        "16720 Route Transcanadienne",
        "Suite 1700",
        "Kirkland, Québec H9H 5M3",
        "Canada"
      ],
      "country": "Canada",
      "contact_name": "Charles Blair",
      "contact_email": "cblair@diversinet.com",
      "contact_phone": "905-816-5131"
    },
    "algorithms": []
  }
}