{
  "metadata": {
    "generated_at": "2026-04-14T03:31:23.958455Z",
    "dataset": "historical",
    "source": "https://csrc.nist.gov/projects/cryptographic-module-validation-program/certificate/260"
  },
  "certificate": {
    "certificate_number": "260",
    "dataset": "historical",
    "generated_at": "2026-04-14T03:31:23.958455Z",
    "nist_page_url": "https://csrc.nist.gov/projects/cryptographic-module-validation-program/certificate/260",
    "certificate_detail_url": "https://csrc.nist.gov/projects/cryptographic-module-validation-program/certificate/260",
    "security_policy_url": "https://csrc.nist.gov/CSRC/media/projects/cryptographic-module-validation-program/documents/security-policies/140sp260.pdf",
    "vendor_name": "Motorola, Inc.",
    "module_name": "Encryption Services Module",
    "standard": "FIPS 140-1",
    "status": "Historical",
    "module_type": "Software",
    "embodiment": "Multi-chip embedded",
    "overall_level": 1,
    "validation_date": "10/8/2002",
    "validation_dates": [
      "10/8/2002"
    ],
    "sunset_date": null,
    "caveat": "When operated in FIPS mode",
    "description": "The Encryption Services Module is incorporated into the operating platform software of the Accompli 009 -- the first wireless communications device to incorporate tri-band GSM and GPRS protocols, telephone functionality, Internet access, e- mail, Triple-DES encryption, WAP browser and short message service (SMS) with a full QWERTY keyboard and 256-color screen.",
    "security_level_exceptions": [
      "EMI/EMC: Level 3",
      "Key Mangement: Level 3",
      "Software Security: Level 3",
      "Operating System Security: Tested as meeting Level 1 with Microware OS-9, Version 2.2 (single user mode)"
    ],
    "related_files": [
      {
        "label": "Security Policy",
        "url": "https://csrc.nist.gov/CSRC/media/projects/cryptographic-module-validation-program/documents/security-policies/140sp260.pdf"
      },
      {
        "label": "Certificate",
        "url": "https://csrc.nist.gov/CSRC/media/projects/cryptographic-module-validation-program/documents/certificates/140crt260.pdf"
      }
    ],
    "validation_history": [
      {
        "date": "10/8/2002",
        "type": "Initial",
        "lab": "UL Verification Services, Inc."
      }
    ],
    "vendor": {
      "name": "Motorola, Inc.",
      "website_url": "http://www.motorola.com",
      "address_lines": [
        "200 N. Center East",
        "Suite 400",
        "Alpharetta, GA 30022",
        "USA"
      ],
      "country": "USA",
      "contact_name": "Christopher Yasko",
      "contact_email": "Chris.Yasko@motorola.com",
      "contact_phone": "770-521-5150"
    },
    "algorithms": []
  }
}