{
  "metadata": {
    "generated_at": "2026-04-14T22:06:10.557502Z",
    "dataset": "historical",
    "source": "https://csrc.nist.gov/projects/cryptographic-module-validation-program/certificate/2632"
  },
  "certificate": {
    "certificate_number": "2632",
    "dataset": "historical",
    "generated_at": "2026-04-14T22:06:10.557502Z",
    "nist_page_url": "https://csrc.nist.gov/projects/cryptographic-module-validation-program/certificate/2632",
    "certificate_detail_url": "https://csrc.nist.gov/projects/cryptographic-module-validation-program/certificate/2632",
    "security_policy_url": "https://csrc.nist.gov/CSRC/media/projects/cryptographic-module-validation-program/documents/security-policies/140sp2632.pdf",
    "vendor_name": "SonicWall, Inc.",
    "module_name": "SonicWALL SM 9800",
    "standard": "FIPS 140-2",
    "status": "Historical",
    "module_type": "Hardware",
    "embodiment": "Multi-Chip Stand Alone",
    "overall_level": 2,
    "validation_date": "5/12/2016, 6/12/2017",
    "validation_dates": [
      "5/12/2016",
      "6/12/2017"
    ],
    "sunset_date": null,
    "caveat": "When operated in FIPS mode",
    "description": "The SonicWALL™ SuperMassive™ Series is SonicWALL's Next-Generation Firewall (NGFW) platform designed for large networks to deliver scalability, reliability and deep security at multi-gigabit speeds with near zero latency.",
    "security_level_exceptions": [
      "Cryptographic Module Specification: Level 3",
      "Design Assurance: Level 3",
      "Mitigation of Other Attacks: N/A"
    ],
    "related_files": [
      {
        "label": "Security Policy",
        "url": "https://csrc.nist.gov/CSRC/media/projects/cryptographic-module-validation-program/documents/security-policies/140sp2632.pdf"
      },
      {
        "label": "Consolidated Certificate",
        "url": "https://csrc.nist.gov/CSRC/media/projects/cryptographic-module-validation-program/documents/certificates/FIPS140ConsolidatedCertMay2016.pdf"
      }
    ],
    "validation_history": [
      {
        "date": "5/12/2016",
        "type": "Initial",
        "lab": "UL Verification Services, Inc."
      },
      {
        "date": "6/12/2017",
        "type": "Update",
        "lab": "UL Verification Services, Inc."
      }
    ],
    "vendor": {
      "name": "SonicWall, Inc.",
      "website_url": "http://www.sonicwall.com",
      "address_lines": [
        "5455 Great America Parkway",
        "Santa Clara, CA 95054",
        "USA"
      ],
      "country": "USA",
      "contact_name": "Lawrence Wagner",
      "contact_email": "lwagner@sonicwall.com",
      "contact_phone": "408-752-7886"
    }
  }
}