{
  "metadata": {
    "generated_at": "2026-04-14T12:11:01.385018Z",
    "dataset": "active",
    "source": "https://csrc.nist.gov/projects/cryptographic-module-validation-program/certificate/4719"
  },
  "certificate": {
    "certificate_number": "4719",
    "dataset": "active",
    "generated_at": "2026-04-14T12:11:01.385018Z",
    "nist_page_url": "https://csrc.nist.gov/projects/cryptographic-module-validation-program/certificate/4719",
    "certificate_detail_url": "https://csrc.nist.gov/projects/cryptographic-module-validation-program/certificate/4719",
    "security_policy_url": "https://csrc.nist.gov/CSRC/media/projects/cryptographic-module-validation-program/documents/security-policies/140sp4719.pdf",
    "vendor_name": "Palo Alto Networks, Inc.",
    "module_name": "Palo Alto Networks SD-WAN Instant-On Network (ION) Devices ION 1200, ION 1200-S, ION 3200, ION 5200, and ION 9200",
    "standard": "FIPS 140-3",
    "status": "Active",
    "module_type": "Hardware",
    "embodiment": "Multi-Chip Stand Alone",
    "overall_level": 2,
    "validation_date": "7/11/2024",
    "validation_dates": [
      "7/11/2024"
    ],
    "sunset_date": "7/10/2029",
    "caveat": "Interim Validation. The tamper evident seals installed as indicated in the Security Policy",
    "description": "The Palo Alto Networks SD-WAN Instant-On Network (ION) Devices (ION 1200, ION 1200-S, ION 3200, ION 5200 and ION 9200) enable the integration of a diverse set of wide area network (WAN) connection types, improve application performance and visibility, enhance security and compliance, and reduce the overall cost and complexity of your WAN.",
    "security_level_exceptions": [
      "Operational environment: N/A",
      "Non-invasive security: N/A",
      "Mitigation of other attacks: N/A"
    ],
    "related_files": [
      {
        "label": "Security Policy",
        "url": "https://csrc.nist.gov/CSRC/media/projects/cryptographic-module-validation-program/documents/security-policies/140sp4719.pdf"
      },
      {
        "label": "Consolidated Certificate",
        "url": "https://csrc.nist.gov/CSRC/media/projects/cryptographic-module-validation-program/documents/certificates/July 2024_010824_1146.pdf"
      }
    ],
    "validation_history": [
      {
        "date": "7/11/2024",
        "type": "Initial",
        "lab": "Gossamer Security Solutions"
      }
    ],
    "vendor": {
      "name": "Palo Alto Networks, Inc.",
      "website_url": "http://www.paloaltonetworks.com",
      "address_lines": [
        "3000 Tannery Way",
        "Santa Clara, CA 95054",
        "USA"
      ],
      "country": "USA",
      "contact_name": "Amir Shahhosseini",
      "contact_email": "certifications@paloaltonetworks.com",
      "contact_phone": "408-753-4000"
    }
  }
}