{
  "metadata": {
    "generated_at": "2026-04-15T02:52:53.715074Z",
    "dataset": "active",
    "source": "https://csrc.nist.gov/projects/cryptographic-module-validation-program/certificate/4906"
  },
  "certificate": {
    "certificate_number": "4906",
    "dataset": "active",
    "generated_at": "2026-04-15T02:52:53.715074Z",
    "nist_page_url": "https://csrc.nist.gov/projects/cryptographic-module-validation-program/certificate/4906",
    "certificate_detail_url": "https://csrc.nist.gov/projects/cryptographic-module-validation-program/certificate/4906",
    "security_policy_url": "https://csrc.nist.gov/CSRC/media/projects/cryptographic-module-validation-program/documents/security-policies/140sp4906.pdf",
    "vendor_name": "FUJIFILM Business Innovation Corp.",
    "module_name": "FUJIFILM BI Cryptographic Kernel Module for WRL",
    "standard": "FIPS 140-3",
    "status": "Active",
    "module_type": "Software",
    "embodiment": "Multi-Chip Stand Alone",
    "overall_level": 1,
    "validation_date": "12/2/2024",
    "validation_dates": [
      "12/2/2024"
    ],
    "sunset_date": "12/1/2026",
    "caveat": "Interim Validation; No assurance of minimum security of SSPs (e.g., keys, bit strings) that are externally loaded, or of SSPs established with externally loaded SSPs.",
    "description": "The module is a software module. The primary purpose of the FUJIFILM BI Cryptographic Kernel Module for WRL is to provide encryption/decryption of data for the multifunction devices.",
    "security_level_exceptions": [
      "Physical security: N/A",
      "Non-invasive security: N/A",
      "Mitigation of other attacks: N/A"
    ],
    "related_files": [
      {
        "label": "Security Policy",
        "url": "https://csrc.nist.gov/CSRC/media/projects/cryptographic-module-validation-program/documents/security-policies/140sp4906.pdf"
      }
    ],
    "validation_history": [
      {
        "date": "12/2/2024",
        "type": "Initial",
        "lab": "Penumbra Security, Inc."
      }
    ],
    "vendor": {
      "name": "FUJIFILM Business Innovation Corp.",
      "website_url": "http://www.fujifilm.com/fbglobal/eng",
      "address_lines": [
        "6-1, Minatomirai, Nishi-ku",
        "Yokohama-shi, Kanagawa 220-8668",
        "Japan"
      ],
      "country": "Japan",
      "contact_name": "Yoshinori Ando",
      "contact_email": "yoshinori.ando.tk@fujifilm.com",
      "contact_phone": "81-45-755-5504"
    }
  }
}