{
  "metadata": {
    "generated_at": "2026-04-12T03:10:00.961597Z",
    "dataset": "active",
    "source": "https://csrc.nist.gov/projects/cryptographic-module-validation-program/certificate/5146"
  },
  "certificate": {
    "certificate_number": "5146",
    "dataset": "active",
    "generated_at": "2026-04-12T03:10:00.961597Z",
    "nist_page_url": "https://csrc.nist.gov/projects/cryptographic-module-validation-program/certificate/5146",
    "certificate_detail_url": "https://csrc.nist.gov/projects/cryptographic-module-validation-program/certificate/5146",
    "security_policy_url": "https://csrc.nist.gov/CSRC/media/projects/cryptographic-module-validation-program/documents/security-policies/140sp5146.pdf",
    "vendor_name": "Amazon Web Services, Inc",
    "module_name": "AWS-LC Cryptographic Module (dynamic)",
    "standard": "FIPS 140-3",
    "status": "Active",
    "module_type": "Software",
    "embodiment": "Multi-Chip Stand Alone",
    "overall_level": 1,
    "validation_date": "1/26/2026",
    "validation_dates": [
      "1/26/2026"
    ],
    "sunset_date": "1/25/2031",
    "caveat": "When operated in approved mode. No assurance of the minimum strength of generated SSPs (e.g., keys)",
    "description": "AWS-LC is a general-purpose cryptographic library maintained by the AWS Cryptography team for AWS and their customers. It іs based on code from the Google BoringSSL project and the OpenSSL project.",
    "security_level_exceptions": [
      "Physical security: N/A",
      "Non-invasive security: N/A"
    ],
    "related_files": [
      {
        "label": "Security Policy",
        "url": "https://csrc.nist.gov/CSRC/media/projects/cryptographic-module-validation-program/documents/security-policies/140sp5146.pdf"
      }
    ],
    "validation_history": [
      {
        "date": "1/26/2026",
        "type": "Initial",
        "lab": "atsec information security corporation"
      }
    ],
    "vendor": {
      "name": "Amazon Web Services, Inc",
      "website_url": "http://aws.amazon.com",
      "address_lines": [
        "1918 8th Ave.",
        "Seattle, WA 98121",
        "USA"
      ],
      "country": "USA",
      "contact_name": "Daryl Martin",
      "contact_email": "aws-fips-external@amazon.com",
      "contact_phone": "0000000000"
    },
    "algorithms": []
  }
}